musicgen/__init__.py
musicgen/__main__.py
musicgen/api.py
musicgen/batch.py
musicgen/cli.py
musicgen/config.py
musicgen/exceptions.py
musicgen/generator.py
musicgen/prompt.py
musicgen/py.typed
musicgen/utils.py
musicgen/web.py
musicgen_unified-2.0.1.dist-info/licenses/LICENSE
musicgen_unified-2.0.1.dist-info/METADATA
musicgen_unified-2.0.1.dist-info/WHEEL
musicgen_unified-2.0.1.dist-info/entry_points.txt
musicgen_unified-2.0.1.dist-info/top_level.txt
musicgen_unified-2.0.1.dist-info/RECORD
