Metadata-Version: 2.4
Name: musicgen-unified
Version: 2.0.1
Summary: Simple, clean instrumental music generation with MusicGen
Home-page: https://github.com/Bright-L01/musicgen-unified
Author: Bright Liu
Author-email: Bright Liu <brightliu@college.harvard.edu>
License: MIT
Project-URL: Homepage, https://github.com/Bright-L01/musicgen-unified
Project-URL: Documentation, https://github.com/Bright-L01/musicgen-unified#readme
Project-URL: Repository, https://github.com/Bright-L01/musicgen-unified
Project-URL: Issues, https://github.com/Bright-L01/musicgen-unified/issues
Classifier: Development Status :: 4 - Beta
Classifier: Intended Audience :: Developers
Classifier: Intended Audience :: Science/Research
Classifier: License :: OSI Approved :: MIT License
Classifier: Programming Language :: Python :: 3
Classifier: Programming Language :: Python :: 3.8
Classifier: Programming Language :: Python :: 3.9
Classifier: Programming Language :: Python :: 3.10
Classifier: Programming Language :: Python :: 3.11
Classifier: Topic :: Multimedia :: Sound/Audio :: Sound Synthesis
Classifier: Topic :: Scientific/Engineering :: Artificial Intelligence
Requires-Python: >=3.8
License-File: LICENSE
Requires-Dist: numpy<2.0,>=1.26.0
Requires-Dist: scipy<2.0,>=1.14.0
Requires-Dist: torch>=2.2.0
Requires-Dist: transformers>=4.43.0
Requires-Dist: scikit-learn>=1.3.0
Requires-Dist: soundfile>=0.12.0
Requires-Dist: librosa>=0.10.0
Requires-Dist: pydub>=0.25.0
Requires-Dist: typer[all]>=0.9.0
Requires-Dist: rich>=13.0.0
Requires-Dist: pandas>=2.0.0
Provides-Extra: api
Requires-Dist: fastapi>=0.100.0; extra == "api"
Requires-Dist: uvicorn[standard]>=0.23.0; extra == "api"
Requires-Dist: python-multipart>=0.0.6; extra == "api"
Provides-Extra: web
Requires-Dist: fastapi>=0.100.0; extra == "web"
Requires-Dist: uvicorn[standard]>=0.23.0; extra == "web"
Provides-Extra: dev
Requires-Dist: pytest>=7.0.0; extra == "dev"
Requires-Dist: pytest-cov>=4.0.0; extra == "dev"
Requires-Dist: black>=23.0.0; extra == "dev"
Requires-Dist: ruff>=0.1.0; extra == "dev"
Requires-Dist: mypy>=1.0.0; extra == "dev"
Requires-Dist: python-semantic-release>=8.0.0; extra == "dev"
Requires-Dist: pre-commit>=3.0.0; extra == "dev"
Requires-Dist: commitizen>=3.0.0; extra == "dev"
Provides-Extra: gpu
Requires-Dist: flash-attn>=2.0.0; extra == "gpu"
Requires-Dist: xformers>=0.0.20; extra == "gpu"
Dynamic: author
Dynamic: home-page
Dynamic: license-file
Dynamic: requires-python
